defeatbeta_api/__init__.py
defeatbeta_api/__version__.py
defeatbeta_api/client/__init__.py
defeatbeta_api/client/duckdb_client.py
defeatbeta_api/client/duckdb_conf.py
defeatbeta_api/client/hugging_face_client.py
defeatbeta_api/data/__init__.py
defeatbeta_api/data/balance_sheet.json
defeatbeta_api/data/balance_sheet.py
defeatbeta_api/data/cash_flow.json
defeatbeta_api/data/cash_flow.py
defeatbeta_api/data/dictionary.json
defeatbeta_api/data/finance_item.py
defeatbeta_api/data/finance_statement.py
defeatbeta_api/data/finance_value.py
defeatbeta_api/data/income_statement.json
defeatbeta_api/data/income_statement.py
defeatbeta_api/data/print_visitor.py
defeatbeta_api/data/statement.py
defeatbeta_api/data/statement_visitor.py
defeatbeta_api/data/stock_statement.py
defeatbeta_api/data/ticker.py
defeatbeta_api/utils/__init__.py
defeatbeta_api/utils/case_insensitive_dict.py
defeatbeta_api/utils/const.py
defeatbeta_api/utils/util.py
defeatbeta_api-0.0.5.dist-info/licenses/LICENSE
defeatbeta_api-0.0.5.dist-info/METADATA
defeatbeta_api-0.0.5.dist-info/WHEEL
defeatbeta_api-0.0.5.dist-info/top_level.txt
defeatbeta_api-0.0.5.dist-info/RECORD
