Metadata-Version: 2.4
Name: defeatbeta-api
Version: 0.0.5
Summary: An open-source alternative to Yahoo Finance's market data APIs with higher reliability.
Author-email: bwzheng2010 <bwzheng2010@gmail.com>
License: Apache-2.0
Project-URL: Homepage, https://github.com/defeat-beta/defeatbeta-api
Project-URL: Bug Tracker, https://github.com/defeat-beta/defeatbeta-api/issues
Requires-Python: >=3.7
License-File: LICENSE
Requires-Dist: duckdb>=1.1.3
Requires-Dist: pandas>=2.2.3
Requires-Dist: requests~=2.32.3
Requires-Dist: psutil>=7.0.0
Requires-Dist: pyfiglet>=1.0.2
Requires-Dist: urllib3~=2.3.0
Requires-Dist: tabulate>=0.9.0
Dynamic: license-file
